febio_python/container/__init__.py
febio_python/container/febio_container.py
febio_python/core/__init__.py
febio_python/core/element_types.py
febio_python/core/enums.py
febio_python/core/meta_data.py
febio_python/feb/__init__.py
febio_python/feb/_caching.py
febio_python/feb/_feb_25.py
febio_python/feb/_feb_30.py
febio_python/feb/_feb_40.py
febio_python/feb/feb_version_handler.py
febio_python/feb/run.py
febio_python/feb/bases/__init__.py
febio_python/feb/bases/abstract_feb.py
febio_python/feb/bases/base_feb.py
febio_python/feb/legacy/FEBio_feb.py
febio_python/feb/legacy/FEBio_xml_handler.py
febio_python/feb/legacy/__init__.py
febio_python/utils/__init__.py
febio_python/utils/enum_utils.py
febio_python/utils/log.py
febio_python/utils/pyvista_utils.py
febio_python/utils/vtk_utils.py
febio_python/xplt/__init__.py
febio_python/xplt/xplt_object.py
febio_python/xplt/xplt_parser/__init__.py
febio_python/xplt/xplt_parser/_binary_file_reader_helpers.py
febio_python/xplt/xplt_parser/_decompress.py
febio_python/xplt/xplt_parser/read_xplt.py
febio_python/xplt/xplt_parser/_spec_30/__init__.py
febio_python/xplt/xplt_parser/_spec_30/_xplt_sections.py
febio_python/xplt/xplt_parser/_spec_30/reader.py
febio_python/xplt/xplt_parser/_spec_40/__init__.py
febio_python/xplt/xplt_parser/_spec_40/reader.py
febio_python/xplt/xplt_parser/legacy/to_json.py
febio_python/xplt/xplt_parser/legacy/common/__init__.py
febio_python/xplt/xplt_parser/legacy/common/database/__init__.py
febio_python/xplt/xplt_parser/legacy/common/database/data_types.py
febio_python/xplt/xplt_parser/legacy/common/database/elem_types.py
febio_python/xplt/xplt_parser/legacy/common/database/nodes_per_elem.py
febio_python/xplt/xplt_parser/legacy/common/database/r_keys.py
febio_python/xplt/xplt_parser/legacy/common/database/tags.py
febio_python/xplt/xplt_parser/legacy/common/json_database/element_types.json
febio_python/xplt/xplt_parser/legacy/common/json_database/nodes_per_elem.json
febio_python-0.2.1.dist-info/LICENSE
febio_python-0.2.1.dist-info/METADATA
febio_python-0.2.1.dist-info/WHEEL
febio_python-0.2.1.dist-info/entry_points.txt
febio_python-0.2.1.dist-info/top_level.txt
febio_python-0.2.1.dist-info/RECORD
