Metadata-Version: 2.1
Name: febio-python
Version: 0.2.1
Summary: Collection of python modules to work with FEBio.
Home-page: https://github.com/Nobregaigor/febio-python
Author: Igor N
License: MIT
Classifier: Programming Language :: Python :: 3
Classifier: License :: OSI Approved :: MIT License
Classifier: Operating System :: OS Independent
Requires-Python: >=3.7
License-File: LICENSE
